sumformer2/__init__.py
sumformer2/main.py
sumformer2/modules.py
sumformer2/transformer.py
sumformer2/utils.py
sumformer2-0.4.2.dist-info/LICENSE
sumformer2-0.4.2.dist-info/METADATA
sumformer2-0.4.2.dist-info/WHEEL
sumformer2-0.4.2.dist-info/entry_points.txt
sumformer2-0.4.2.dist-info/top_level.txt
sumformer2-0.4.2.dist-info/RECORD
