Metadata-Version: 2.1
Name: sumformer2
Version: 0.4.2
Summary: Summarisation Transformer 2
Home-page: https://github.com/Ryan-Ott/sumformer2
Author: Ryan Ott
Author-email: ott.r21@gmail.com
License-File: LICENSE
Requires-Dist: absl-py (==1.4.0)
Requires-Dist: aiohttp (==3.8.4)
Requires-Dist: aiosignal (==1.3.1)
Requires-Dist: appdirs (==1.4.4)
Requires-Dist: async-timeout (==4.0.2)
Requires-Dist: attrs (==23.1.0)
Requires-Dist: bert-score (==0.3.13)
Requires-Dist: bleach (==6.0.0)
Requires-Dist: certifi (==2023.5.7)
Requires-Dist: charset-normalizer (==3.1.0)
Requires-Dist: click (==8.1.3)
Requires-Dist: contourpy (==1.1.0)
Requires-Dist: cycler (==0.11.0)
Requires-Dist: datasets (==2.12.0)
Requires-Dist: dill (==0.3.6)
Requires-Dist: docker-pycreds (==0.4.0)
Requires-Dist: docopt (==0.6.2)
Requires-Dist: docutils (==0.20.1)
Requires-Dist: filelock (==3.12.0)
Requires-Dist: fire (==0.5.0)
Requires-Dist: fonttools (==4.40.0)
Requires-Dist: frozenlist (==1.3.3)
Requires-Dist: fsspec (==2023.5.0)
Requires-Dist: gitdb (==4.0.10)
Requires-Dist: GitPython (==3.1.31)
Requires-Dist: huggingface-hub (==0.15.1)
Requires-Dist: idna (==3.4)
Requires-Dist: importlib-metadata (==6.6.0)
Requires-Dist: jaraco.classes (==3.2.3)
Requires-Dist: Jinja2 (==3.1.2)
Requires-Dist: joblib (==1.2.0)
Requires-Dist: keyring (==23.13.1)
Requires-Dist: kiwisolver (==1.4.4)
Requires-Dist: markdown-it-py (==3.0.0)
Requires-Dist: MarkupSafe (==2.1.3)
Requires-Dist: matplotlib (==3.7.1)
Requires-Dist: mdurl (==0.1.2)
Requires-Dist: more-itertools (==9.1.0)
Requires-Dist: mpmath (==1.3.0)
Requires-Dist: multidict (==6.0.4)
Requires-Dist: multiprocess (==0.70.14)
Requires-Dist: networkx (==3.1)
Requires-Dist: nltk (==3.8.1)
Requires-Dist: numpy (==1.24.3)
Requires-Dist: packaging (==23.1)
Requires-Dist: pandas (==2.0.2)
Requires-Dist: pathtools (==0.1.2)
Requires-Dist: Pillow (==9.5.0)
Requires-Dist: pipreqs (==0.4.13)
Requires-Dist: pkginfo (==1.9.6)
Requires-Dist: protobuf (==4.23.2)
Requires-Dist: psutil (==5.9.5)
Requires-Dist: pyarrow (==12.0.0)
Requires-Dist: Pygments (==2.15.1)
Requires-Dist: pyparsing (==3.0.9)
Requires-Dist: python-dateutil (==2.8.2)
Requires-Dist: pytz (==2023.3)
Requires-Dist: PyYAML (==6.0)
Requires-Dist: readme-renderer (==37.3)
Requires-Dist: regex (==2023.6.3)
Requires-Dist: requests (==2.31.0)
Requires-Dist: requests-toolbelt (==1.0.0)
Requires-Dist: responses (==0.18.0)
Requires-Dist: rfc3986 (==2.0.0)
Requires-Dist: rich (==13.4.2)
Requires-Dist: rouge (==1.0.1)
Requires-Dist: rouge-score (==0.1.2)
Requires-Dist: sentencepiece (==0.1.99)
Requires-Dist: sentry-sdk (==1.25.0)
Requires-Dist: setproctitle (==1.3.2)
Requires-Dist: six (==1.16.0)
Requires-Dist: smmap (==5.0.0)
Requires-Dist: sympy (==1.12)
Requires-Dist: termcolor (==2.3.0)
Requires-Dist: tokenizers (==0.13.3)
Requires-Dist: torch (==2.0.1)
Requires-Dist: tqdm (==4.65.0)
Requires-Dist: transformers (==4.29.2)
Requires-Dist: twine (==4.0.2)
Requires-Dist: typing-extensions (==4.6.3)
Requires-Dist: tzdata (==2023.3)
Requires-Dist: urllib3 (==2.0.3)
Requires-Dist: wandb (==0.15.4)
Requires-Dist: webencodings (==0.5.1)
Requires-Dist: xxhash (==3.2.0)
Requires-Dist: yarg (==0.1.9)
Requires-Dist: yarl (==1.9.2)
Requires-Dist: zipp (==3.15.0)
